{"Snake":{"Head":{"X":15,"Y":12,"Color":8,"PixelSize":3},"Body":[{"X":10,"Y":6,"Color":15,"PixelSize":3},{"X":10,"Y":7,"Color":15,"PixelSize":3},{"X":10,"Y":8,"Color":15,"PixelSize":3},{"X":10,"Y":9,"Color":15,"PixelSize":3},{"X":11,"Y":9,"Color":15,"PixelSize":3},{"X":12,"Y":9,"Color":15,"PixelSize":3},{"X":13,"Y":9,"Color":15,"PixelSize":3},{"X":14,"Y":9,"Color":15,"PixelSize":3},{"X":15,"Y":9,"Color":15,"PixelSize":3},{"X":15,"Y":8,"Color":15,"PixelSize":3},{"X":15,"Y":7,"Color":15,"PixelSize":3},{"X":16,"Y":7,"Color":15,"PixelSize":3},{"X":17,"Y":7,"Color":15,"PixelSize":3},{"X":18,"Y":7,"Color":15,"PixelSize":3},{"X":18,"Y":8,"Color":15,"PixelSize":3},{"X":18,"Y":9,"Color":15,"PixelSize":3},{"X":18,"Y":10,"Color":15,"PixelSize":3},{"X":18,"Y":11,"Color":15,"PixelSize":3},{"X":18,"Y":12,"Color":15,"PixelSize":3},{"X":17,"Y":12,"Color":15,"PixelSize":3},{"X":16,"Y":12,"Color":15,"PixelSize":3}]},"Food":{"X":26,"Y":6,"Color":10,"PixelSize":3},"Score":24,"PlayerName":"storkych"}